[
  {
    "Tag": "0",
    "showType": 0,
    "Text": "9-M1",
    "RelativeX": 0.026078235,
    "RelativeY": 0.1325167,
    "Width": 60,
    "Height": 30,
    "BackColor": "White",
    "ForeColor": "Blue",
    "FontName": "Microsoft Sans Serif",
    "FontSize": 10.0,
    "ToolList": []
  },
  {
    "Tag": "1",
    "showType": 0,
    "Text": "9-M2",
    "RelativeX": 0.034102306,
    "RelativeY": 0.39309576,
    "Width": 60,
    "Height": 30,
    "BackColor": "White",
    "ForeColor": "Blue",
    "FontName": "Microsoft Sans Serif",
    "FontSize": 10.0,
    "ToolList": []
  },
  {
    "Tag": "2",
    "showType": 0,
    "Text": "14-M1",
    "RelativeX": 0.045135405,
    "RelativeY": 0.5902004,
    "Width": 60,
    "Height": 30,
    "BackColor": "#C3D69B",
    "ForeColor": "Red",
    "FontName": "Microsoft Sans Serif",
    "FontSize": 10.0,
    "ToolList": []
  },
  {
    "Tag": "3",
    "showType": 0,
    "Text": "7-M",
    "RelativeX": 0.045135405,
    "RelativeY": 0.63808465,
    "Width": 60,
    "Height": 30,
    "BackColor": "White",
    "ForeColor": "Blue",
    "FontName": "Microsoft Sans Serif",
    "FontSize": 10.0,
    "ToolList": []
  },
  {
    "Tag": "4",
    "showType": 0,
    "Text": "14-M2",
    "RelativeX": 0.04112337,
    "RelativeY": 0.6982183,
    "Width": 60,
    "Height": 30,
    "BackColor": "#C3D69B",
    "ForeColor": "Red",
    "FontName": "Microsoft Sans Serif",
    "FontSize": 10.0,
    "ToolList": []
  },
  {
    "Tag": "5",
    "showType": 0,
    "Text": "11-M",
    "RelativeX": 0.049147442,
    "RelativeY": 0.76391983,
    "Width": 60,
    "Height": 30,
    "BackColor": "White",
    "ForeColor": "Blue",
    "FontName": "Microsoft Sans Serif",
    "FontSize": 10.0,
    "ToolList": []
  },
  {
    "Tag": "6",
    "showType": 0,
    "Text": "14-M3",
    "RelativeX": 0.026078235,
    "RelativeY": 0.811804,
    "Width": 60,
    "Height": 30,
    "BackColor": "#C3D69B",
    "ForeColor": "Red",
    "FontName": "Microsoft Sans Serif",
    "FontSize": 10.0,
    "ToolList": []
  },
  {
    "Tag": "7",
    "showType": 0,
    "Text": "1-C",
    "RelativeX": 0.17051153,
    "RelativeY": 0.030066814,
    "Width": 60,
    "Height": 30,
    "BackColor": "White",
    "ForeColor": "Blue",
    "FontName": "Microsoft Sans Serif",
    "FontSize": 10.0,
    "ToolList": []
  },
  {
    "Tag": "8",
    "showType": 0,
    "Text": "2-C",
    "RelativeX": 0.30290872,
    "RelativeY": 0.026726058,
    "Width": 60,
    "Height": 30,
    "BackColor": "White",
    "ForeColor": "Blue",
    "FontName": "Microsoft Sans Serif",
    "FontSize": 10.0,
    "ToolList": []
  },
  {
    "Tag": "9",
    "showType": 0,
    "Text": "2-S",
    "RelativeX": 0.37211636,
    "RelativeY": 0.026726058,
    "Width": 60,
    "Height": 30,
    "BackColor": "Red",
    "ForeColor": "Yellow",
    "FontName": "Microsoft Sans Serif",
    "FontSize": 10.0,
    "ToolList": []
  },
  {
    "Tag": "10",
    "showType": 0,
    "Text": "3-M1",
    "RelativeX": 0.45837513,
    "RelativeY": 0.024498885,
    "Width": 60,
    "Height": 30,
    "BackColor": "White",
    "ForeColor": "Blue",
    "FontName": "Microsoft Sans Serif",
    "FontSize": 10.0,
    "ToolList": []
  },
  {
    "Tag": "11",
    "showType": 0,
    "Text": "4-C",
    "RelativeX": 0.52457374,
    "RelativeY": 0.024498885,
    "Width": 60,
    "Height": 30,
    "BackColor": "White",
    "ForeColor": "Blue",
    "FontName": "Microsoft Sans Serif",
    "FontSize": 10.0,
    "ToolList": []
  },
  {
    "Tag": "12",
    "showType": 0,
    "Text": "10-M1",
    "RelativeX": 0.50451356,
    "RelativeY": 0.5011136,
    "Width": 60,
    "Height": 30,
    "BackColor": "White",
    "ForeColor": "Blue",
    "FontName": "Microsoft Sans Serif",
    "FontSize": 10.0,
    "ToolList": []
  },
  {
    "Tag": "13",
    "showType": 0,
    "Text": "14-M5",
    "RelativeX": 0.5977934,
    "RelativeY": 0.49665925,
    "Width": 60,
    "Height": 30,
    "BackColor": "#C3D69B",
    "ForeColor": "Red",
    "FontName": "Microsoft Sans Serif",
    "FontSize": 10.0,
    "ToolList": []
  },
  {
    "Tag": "14",
    "showType": 0,
    "Text": "14-M6",
    "RelativeX": 0.665998,
    "RelativeY": 0.49665925,
    "Width": 60,
    "Height": 30,
    "BackColor": "#C3D69B",
    "ForeColor": "Red",
    "FontName": "Microsoft Sans Serif",
    "FontSize": 10.0,
    "ToolList": []
  },
  {
    "Tag": "15",
    "showType": 0,
    "Text": "12-M1",
    "RelativeX": 0.13139418,
    "RelativeY": 0.518931,
    "Width": 60,
    "Height": 30,
    "BackColor": "Blue",
    "ForeColor": "White",
    "FontName": "Microsoft Sans Serif",
    "FontSize": 10.0,
    "ToolList": []
  },
  {
    "Tag": "16",
    "showType": 0,
    "Text": "12-M",
    "RelativeX": 0.19458374,
    "RelativeY": 0.518931,
    "Width": 60,
    "Height": 30,
    "BackColor": "White",
    "ForeColor": "Blue",
    "FontName": "Microsoft Sans Serif",
    "FontSize": 10.0,
    "ToolList": []
  },
  {
    "Tag": "17",
    "showType": 0,
    "Text": "5-M3",
    "RelativeX": 0.43630892,
    "RelativeY": 0.52115816,
    "Width": 60,
    "Height": 30,
    "BackColor": "Blue",
    "ForeColor": "White",
    "FontName": "Microsoft Sans Serif",
    "FontSize": 10.0,
    "ToolList": []
  },
  {
    "Tag": "18",
    "showType": 0,
    "Text": "14-M4",
    "RelativeX": 0.554664,
    "RelativeY": 0.53563476,
    "Width": 60,
    "Height": 30,
    "BackColor": "#C3D69B",
    "ForeColor": "Red",
    "FontName": "Microsoft Sans Serif",
    "FontSize": 10.0,
    "ToolList": []
  },
  {
    "Tag": "19",
    "showType": 0,
    "Text": "14-M8",
    "RelativeX": 0.60581744,
    "RelativeY": 0.7026726,
    "Width": 60,
    "Height": 30,
    "BackColor": "#C3D69B",
    "ForeColor": "Red",
    "FontName": "Microsoft Sans Serif",
    "FontSize": 10.0,
    "ToolList": []
  },
  {
    "Tag": "20",
    "showType": 0,
    "Text": "14-M9",
    "RelativeX": 0.67101306,
    "RelativeY": 0.73162585,
    "Width": 60,
    "Height": 30,
    "BackColor": "#C3D69B",
    "ForeColor": "Red",
    "FontName": "Microsoft Sans Serif",
    "FontSize": 10.0,
    "ToolList": []
  },
  {
    "Tag": "21",
    "showType": 0,
    "Text": "12-M2",
    "RelativeX": 0.22668004,
    "RelativeY": 0.7828508,
    "Width": 60,
    "Height": 30,
    "BackColor": "Blue",
    "ForeColor": "White",
    "FontName": "Microsoft Sans Serif",
    "FontSize": 10.0,
    "ToolList": []
  },
  {
    "Tag": "22",
    "showType": 0,
    "Text": "5-C",
    "RelativeX": 0.7552658,
    "RelativeY": 0.024498885,
    "Width": 60,
    "Height": 30,
    "BackColor": "White",
    "ForeColor": "Blue",
    "FontName": "Microsoft Sans Serif",
    "FontSize": 10.0,
    "ToolList": []
  },
  {
    "Tag": "23",
    "showType": 0,
    "Text": "3-M2",
    "RelativeX": 0.82647943,
    "RelativeY": 0.023385301,
    "Width": 60,
    "Height": 30,
    "BackColor": "White",
    "ForeColor": "Blue",
    "FontName": "Microsoft Sans Serif",
    "FontSize": 10.0,
    "ToolList": []
  },
  {
    "Tag": "24",
    "showType": 0,
    "Text": "14-M7",
    "RelativeX": 0.777332,
    "RelativeY": 0.4922049,
    "Width": 60,
    "Height": 30,
    "BackColor": "#C3D69B",
    "ForeColor": "Red",
    "FontName": "Microsoft Sans Serif",
    "FontSize": 10.0,
    "ToolList": []
  },
  {
    "Tag": "25",
    "showType": 0,
    "Text": "10-M2",
    "RelativeX": 0.8455366,
    "RelativeY": 0.513363,
    "Width": 60,
    "Height": 30,
    "BackColor": "White",
    "ForeColor": "Blue",
    "FontName": "Microsoft Sans Serif",
    "FontSize": 10.0,
    "ToolList": []
  },
  {
    "Tag": "26",
    "showType": 0,
    "Text": "8-M",
    "RelativeX": 0.7261785,
    "RelativeY": 0.53452116,
    "Width": 60,
    "Height": 30,
    "BackColor": "White",
    "ForeColor": "Blue",
    "FontName": "Microsoft Sans Serif",
    "FontSize": 10.0,
    "ToolList": []
  },
  {
    "Tag": "27",
    "showType": 0,
    "Text": "6-M",
    "RelativeX": 0.9207623,
    "RelativeY": 0.3040089,
    "Width": 60,
    "Height": 30,
    "BackColor": "White",
    "ForeColor": "Blue",
    "FontName": "Microsoft Sans Serif",
    "FontSize": 10.0,
    "ToolList": []
  }
]